[
    {
        "id":"01",
        "title":"Basic V-Neck",
        "price": 19.77,
        "brand":"Copper Thompson",
        "stock": 8,
        "rating":4.5,
        "details":"Look your best with this simple, but stylish t-shirt.  This basic short-sleeve tee is made from a soft Cotton and Polyester blend and is guaranteed not to shrink or fade.",
        "category":"t-shirt",
        "for": "male",
        "img":"https://cdn.shopify.com/s/files/1/2617/9878/products/avenue-shopify-theme-mens-tops-23_600x.jpg?v=1642781414"
    },
    {
        "id":"02",
        "title":"Casual V-Neck",
        "price": 15.95,
        "brand":"Copper Thompson",
        "stock": 4,
        "rating":4.8,
        "details":"Look your best with this simple, but stylish t-shirt.  This basic short-sleeve tee is made from a soft Cotton and Polyester blend and is guaranteed not to shrink or fade.",
        "category":"t-shirt",
        "for": "male",
        "img":"https://cdn.shopify.com/s/files/1/2617/9878/products/avenue-shopify-theme-mens-tops-31_600x.jpg?v=1533834117"
    },
    {
        "id":"03",
        "title":"Blue Accent V-Neck",
        "price": 11.55,
        "brand":"Copper Thompson",
        "stock": 7,
        "rating":4.7,
        "details":"Look your best with this simple, but stylish t-shirt.  This basic short-sleeve tee is made from a soft Cotton and Polyester blend and is guaranteed not to shrink or fade.",
        "category":"t-shirt",
        "for": "male",
        "img":"https://cdn.shopify.com/s/files/1/2617/9878/products/avenue-shopify-theme-mens-tops-28_600x.jpg?v=1533834064"
    },
    {
        "id":"04",
        "title":"Avenue Tee",
        "price": 14.99,
        "brand":"KD",
        "stock": 9,
        "rating":4.9,
        "details":"Look your best with this simple, but stylish t-shirt.  This basic short-sleeve tee is made from a soft Cotton and Polyester blend and is guaranteed not to shrink or fade.",
        "category":"t-shirt",
        "for": "male",
        "img":"https://cdn.shopify.com/s/files/1/2617/9878/products/avenue-shopify-theme-mens-tops-24_b6971761-fc01-4aed-94d5-f2c49df837dc_600x.jpg?v=1647621151"
    },
    {
        "id":"05",
        "title":"Basic T-Shirt",
        "price": 12.75,
        "brand":"KD",
        "stock": 10,
        "rating":4.5,
        "details":"Simple style will help you look your best.  This basic short-sleeve tee is made from a soft Cotton and Polyester blend and is guaranteed not to shrink or fade.",
        "category":"t-shirt",
        "for": "male",
        "img":"https://cdn.shopify.com/s/files/1/2617/9878/products/avenue-shopify-theme-mens-tops-2_600x.jpg?v=1608135079"
    },
    {
        "id":"06",
        "title":"Accent V-Neck",
        "price": 16.80,
        "brand":"Keystone",
        "stock": 5,
        "rating":4.8,
        "details":"Simple style will help you look your best.  This basic short-sleeve tee is made from a soft Cotton and Polyester blend and is guaranteed not to shrink or fade.",
        "category":"t-shirt",
        "for": "male",
        "img":"https://cdn.shopify.com/s/files/1/2617/9878/products/avenue-shopify-theme-mens-tops-30_600x.jpg?v=1533834085"
    },
    {
        "id":"07",
        "title":"Soft Cotton V-Neck",
        "price": 19.90,
        "brand":"Keystone",
        "stock": 8,
        "rating":4.6,
        "details":"Simple style will help you look your best.  This basic short-sleeve tee is made from a soft Cotton and Polyester blend and is guaranteed not to shrink or fade.",
        "category":"t-shirt",
        "for": "male",
        "img":"https://cdn.shopify.com/s/files/1/2617/9878/products/avenue-shopify-theme-mens-tops-33_600x.jpg?v=1533834203"
    },
    {
        "id":"08",
        "title":"Comfy V-Neck",
        "price": 15.10,
        "brand":"KD",
        "stock": 3,
        "rating":4.9,
        "details":"Simple style will help you look your best.  This basic short-sleeve tee is made from a soft Cotton and Polyester blend and is guaranteed not to shrink or fade.",
        "category":"t-shirt",
        "for": "male",
        "img":"https://cdn.shopify.com/s/files/1/2617/9878/products/avenue-shopify-theme-mens-tops-32_600x.jpg?v=1533834163"
    },
    {
        "id":"09",
        "title":"Basic V-Neck",
        "price": 14.10,
        "brand":"Keystone",
        "stock": 10,
        "rating":4.5,
        "details":"Look your best with this simple, but stylish t-shirt.  This basic short-sleeve tee is made from a soft Cotton and Polyester blend and is guaranteed not to shrink or fade.",
        "category":"t-shirt",
        "for": "male",
        "img":"https://cdn.shopify.com/s/files/1/2617/9878/products/avenue-shopify-theme-mens-tops-26_600x.jpg?v=1642781414"
    },
    {
        "id":"10",
        "title":"Basic Polo",
        "price": 20.10,
        "brand":"Copper Thompson",
        "stock": 5,
        "rating":4.1,
        "details":"Help him look his best with this simple, but stylish polo.  This basic short-sleeve polo is made from a soft Cotton and Polyester blend and is guaranteed not to shrink or fade.",
        "category":"t-shirt",
        "for": "male",
        "img":"https://cdn.shopify.com/s/files/1/2617/9878/products/avenue-shopify-theme-mens-tops-14_600x.jpg?v=1533832471"
    },
    {
        "id":"11",
        "title":"Checkered Polo",
        "price": 17.55,
        "brand":"KD",
        "stock": 7,
        "rating":4.8,
        "details":"Help him look his best with this simple, but stylish polo.  This basic short-sleeve polo is made from a soft Cotton and Polyester blend and is guaranteed not to shrink or fade.",
        "category":"t-shirt",
        "for": "male",
        "img":"https://cdn.shopify.com/s/files/1/2617/9878/products/avenue-shopify-theme-mens-tops-19_600x.jpg?v=1533832286"
    },
    {
        "id":"12",
        "title":"Blue Striped Polo",
        "price": 17.55,
        "brand":"KD",
        "stock": 6,
        "rating":3.9,
        "details":"Help him look his best with this simple, but stylish polo.  This basic short-sleeve polo is made from a soft Cotton and Polyester blend and is guaranteed not to shrink or fade.",
        "category":"t-shirt",
        "for": "male",
        "img":"https://cdn.shopify.com/s/files/1/2617/9878/products/avenue-shopify-theme-mens-tops-17_600x.jpg?v=1533832056"
    },
    {
        "id":"13",
        "title":"Black Striped Polo",
        "price": 17.55,
        "brand":"Copper Thompson",
        "stock": 7,
        "rating":4.5,
        "details":"Help him look his best with this simple, but stylish polo.  This basic short-sleeve polo is made from a soft Cotton and Polyester blend and is guaranteed not to shrink or fade.",
        "category":"t-shirt",
        "for": "male",
        "img":"https://cdn.shopify.com/s/files/1/2617/9878/products/avenue-shopify-theme-mens-tops-29_600x.jpg?v=1533832204"
    },
    {
        "id":"14",
        "title":"Orange Striped Polo",
        "price": 15.55,
        "brand":"Keystone",
        "stock": 4,
        "rating":4.7,
        "details":"Help him look his best with this simple, but stylish polo.  This basic short-sleeve polo is made from a soft Cotton and Polyester blend and is guaranteed not to shrink or fade.",
        "category":"t-shirt",
        "for": "male",
        "img":"https://cdn.shopify.com/s/files/1/2617/9878/products/avenue-shopify-theme-mens-tops-21_600x.jpg?v=1533832238"
    },
    {
        "id":"15",
        "title":"Drawstring Hoodie",
        "price": 38.99,
        "brand":"Copper Thompson",
        "stock": 6,
        "rating":4.5,
        "details":"Help him look his best with this simple, but stylish hoodie.  This basic pulloveris made from a soft Cotton and Polyester blend and is guaranteed not to shrink or fade.",
        "category":"hoodie",
        "for": "male",
        "img":"https://cdn.shopify.com/s/files/1/2617/9878/products/avenue-shopify-theme-mens-tops-4_600x.jpg?v=1533830723"
    },
    {
        "id":"16",
        "title":"Zippered Hoodie",
        "price": 34.95,
        "brand":"Copper Thompson",
        "stock": 3,
        "rating":4.0,
        "details":"Help him look his best with this simple, but stylish hoodie.  This basic pulloveris made from a soft Cotton and Polyester blend and is guaranteed not to shrink or fade.",
        "category":"hoodie",
        "for": "male",
        "img":"https://cdn.shopify.com/s/files/1/2617/9878/products/avenue-shopify-theme-mens-tops-8_600x.jpg?v=1533831065"
    },
    {
        "id":"17",
        "title":"Basic Hoodie",
        "price": 24.95,
        "brand":"KD",
        "stock": 9,
        "rating":4.8,
        "details":"Help him look his best with this simple, but stylish hoodie.  This basic pulloveris made from a soft Cotton and Polyester blend and is guaranteed not to shrink or fade.",
        "category":"hoodie",
        "for": "male",
        "img":"https://cdn.shopify.com/s/files/1/2617/9878/products/avenue-shopify-theme-mens-tops-9_600x.jpg?v=1533831212"
    },
    {
        "id":"18",
        "title":"Elbow Patch Hoodie",
        "price": 34.95,
        "brand":"Keystone",
        "stock": 4,
        "rating":4.1,
        "details":"Help him look his best with this simple, but stylish hoodie.  This basic pulloveris made from a soft Cotton and Polyester blend and is guaranteed not to shrink or fade.",
        "category":"hoodie",
        "for": "male",
        "img":"https://cdn.shopify.com/s/files/1/2617/9878/products/avenue-shopify-theme-mens-tops-11_600x.jpg?v=1533830557"
    },
    {
        "id":"19",
        "title":"Flannel Hoodie",
        "price": 38.99,
        "brand":"KD",
        "stock": 8,
        "rating":4.6,
        "details":"Help him look his best with this simple, but stylish hoodie.  This basic pulloveris made from a soft Cotton and Polyester blend and is guaranteed not to shrink or fade.",
        "category":"hoodie",
        "for": "male",
        "img":"https://cdn.shopify.com/s/files/1/2617/9878/products/avenue-shopify-theme-mens-tops-6_600x.jpg?v=1533830617"
    },
    {
        "id":"20",
        "title":"Pullover Hoodie",
        "price": 29.99,
        "brand":"Keystone",
        "stock": 7,
        "rating":4.0,
        "details":"Help him look his best with this simple, but stylish hoodie.  This basic pulloveris made from a soft Cotton and Polyester blend and is guaranteed not to shrink or fade.",
        "category":"hoodie",
        "for": "male",
        "img":"https://cdn.shopify.com/s/files/1/2617/9878/products/avenue-shopify-theme-mens-tops-5_600x.jpg?v=1533831683"
    },
    {
        "id":"21",
        "title":"Elbow Patch Button Down",
        "price": 22.50,
        "brand":"Copper Thompson",
        "stock": 9,
        "rating":4.5,
        "details":"Help him look his best with this simple, but stylish hoodie.  This basic pulloveris made from a soft Cotton and Polyester blend and is guaranteed not to shrink or fade.",
        "category":"shirts",
        "for": "male",
        "img":"https://cdn.shopify.com/s/files/1/2617/9878/products/avenue-shopify-theme-mens-tops-36_600x.jpg?v=1533831812"
    },
    {
        "id":"22",
        "title":"Red Plaid Button Down",
        "price": 22.50,
        "brand":"keystone",
        "stock": 4,
        "rating":4.3,
        "details":"Help him look his best with this simple, but stylish hoodie.  This basic pulloveris made from a soft Cotton and Polyester blend and is guaranteed not to shrink or fade.",
        "category":"shirts",
        "for": "male",
        "img":"https://cdn.shopify.com/s/files/1/2617/9878/products/avenue-shopify-theme-mens-tops-34_600x.jpg?v=1533831979"
    },
    {
        "id":"23",
        "title":"Blue Plaid Button Down",
        "price": 22.50,
        "brand":"Copper Thompson",
        "stock": 7,
        "rating":4.1,
        "details":"Help him look his best with this simple, but stylish hoodie.  This basic pulloveris made from a soft Cotton and Polyester blend and is guaranteed not to shrink or fade.",
        "category":"shirts",
        "for": "male",
        "img":"https://cdn.shopify.com/s/files/1/2617/9878/products/avenue-shopify-theme-mens-tops-35_600x.jpg?v=1533831930"
    },
    {
        "id":"24",
        "title":"Faded Jeans",
        "price": 25.95,
        "brand":"Copper Thompson",
        "stock": 7,
        "rating":4.8,
        "details":"Help him look his best with this simple, but stylish hoodie.  This basic pulloveris made from a soft Cotton and Polyester blend and is guaranteed not to shrink or fade.",
        "category":"jeans",
        "for": "male",
        "img":"https://cdn.shopify.com/s/files/1/2617/9878/products/avenue-shopify-theme-mens-bottoms-6_600x.jpg?v=1583793050"
    },
    {
        "id":"25",
        "title":"Brown Jeans",
        "price": 23.49,
        "brand":"KD",
        "stock": 5,
        "rating":4.2,
        "details":"Help him look his best with this simple, but stylish hoodie.  This basic pulloveris made from a soft Cotton and Polyester blend and is guaranteed not to shrink or fade.",
        "category":"jeans",
        "for": "male",
        "img":"https://cdn.shopify.com/s/files/1/2617/9878/products/avenue-shopify-theme-mens-bottoms-5_600x.jpg?v=1583793065"
    },
    {
        "id":"26",
        "title":"No Frills Jeans",
        "price": 19.95,
        "brand":"Copper Thompson",
        "stock": 3,
        "rating":4.7,
        "details":"Help him look his best with this simple, but stylish hoodie.  This basic pulloveris made from a soft Cotton and Polyester blend and is guaranteed not to shrink or fade.",
        "category":"jeans",
        "for": "male",
        "img":"https://cdn.shopify.com/s/files/1/2617/9878/products/avenue-shopify-theme-mens-bottoms-2_600x.jpg?v=1583793006"
    },
    {
        "id":"27",
        "title":"Khaki Jeans",
        "price": 23.95,
        "brand":"keystone",
        "stock": 3,
        "rating":4.5,
        "details":"Help him look his best with this simple, but stylish hoodie.  This basic pulloveris made from a soft Cotton and Polyester blend and is guaranteed not to shrink or fade.",
        "category":"jeans",
        "for": "male",
        "img":"https://cdn.shopify.com/s/files/1/2617/9878/products/avenue-shopify-theme-mens-bottoms-4_600x.jpg?v=1583793051"
    },
    {
        "id":"28",
        "title":"Dark Jeans",
        "price": 20.99,
        "brand":"KD",
        "stock": 7,
        "rating":4.0,
        "details":"Help him look his best with this simple, but stylish hoodie.  This basic pulloveris made from a soft Cotton and Polyester blend and is guaranteed not to shrink or fade.",
        "category":"jeans",
        "for": "male",
        "img":"https://cdn.shopify.com/s/files/1/2617/9878/products/avenue-shopify-theme-mens-bottoms-3_600x.jpg?v=1583793059"
    },
    {
        "id":"29",
        "title":"Cargo Shorts",
        "price": 17.99,
        "brand":"KD",
        "stock": 5,
        "rating":4.5,
        "details":"Help him look his best with this simple, but stylish hoodie.  This basic pulloveris made from a soft Cotton and Polyester blend and is guaranteed not to shrink or fade.",
        "category":"shorts",
        "for": "male",
        "img":"https://cdn.shopify.com/s/files/1/2617/9878/products/avenue-shopify-theme-mens-bottoms-17_600x.jpg?v=1533828251"
    },
    {
        "id":"30",
        "title":"Grey Striped Shorts",
        "price": 15.99,
        "brand":"Copper Thompson",
        "stock": 3,
        "rating":4.8,
        "details":"Help him look his best with this simple, but stylish hoodie.  This basic pulloveris made from a soft Cotton and Polyester blend and is guaranteed not to shrink or fade.",
        "category":"shorts",
        "for": "male",
        "img":"https://cdn.shopify.com/s/files/1/2617/9878/products/avenue-shopify-theme-mens-bottoms-18_600x.jpg?v=1533828160"
    },
    {
        "id":"31",
        "title":"Brown Plaid Shorts",
        "price": 15.99,
        "brand":"Copper Thompson",
        "stock": 6,
        "rating":4.3,
        "details":"Help him look his best with this simple, but stylish hoodie.  This basic pulloveris made from a soft Cotton and Polyester blend and is guaranteed not to shrink or fade.",
        "category":"shorts",
        "for": "male",
        "img":"https://cdn.shopify.com/s/files/1/2617/9878/products/avenue-shopify-theme-mens-bottoms-19_600x.jpg?v=1533828088"
    },
    {
        "id":"32",
        "title":"Cuffed Khaki Shorts",
        "price": 17.99,
        "brand":"Keystone",
        "stock": 5,
        "rating":4.1,
        "details":"Help him look his best with this simple, but stylish hoodie.  This basic pulloveris made from a soft Cotton and Polyester blend and is guaranteed not to shrink or fade.",
        "category":"shorts",
        "for": "male",
        "img":"https://cdn.shopify.com/s/files/1/2617/9878/products/avenue-shopify-theme-mens-bottoms-20_600x.jpg?v=1533828028"
    },
    {
        "id":"33",
        "title":"Cuffed Gray Khaki Shorts",
        "price": 19.99,
        "brand":"Copper Thompson",
        "stock": 2,
        "rating":4.5,
        "details":"Help him look his best with this simple, but stylish hoodie.  This basic pulloveris made from a soft Cotton and Polyester blend and is guaranteed not to shrink or fade.",
        "category":"shorts",
        "for": "male",
        "img":"https://cdn.shopify.com/s/files/1/2617/9878/products/avenue-shopify-theme-mens-bottoms-21_600x.jpg?v=1533827956"
    },
    {
        "id":"34",
        "title":"Jorts",
        "price": 13.99,
        "brand":"KD",
        "stock": 5,
        "rating":4.1,
        "details":"Help him look his best with this simple, but stylish hoodie.  This basic pulloveris made from a soft Cotton and Polyester blend and is guaranteed not to shrink or fade.",
        "category":"shorts",
        "for": "male",
        "img":"https://cdn.shopify.com/s/files/1/2617/9878/products/avenue-shopify-theme-mens-bottoms-22_600x.jpg?v=1533827756"
    },
    {
        "id":"35",
        "title":"Sleeveless Dress",
        "price": 34.49,
        "brand":"KD",
        "stock": 5,
        "rating":4.5,
        "details":"Feel your best with this simple, but stylish long sleeve T dress.  This basic dress is made from a soft Cotton and Polyester blend and is guaranteed not to shrink  or fade.",
        "category":"dress",
        "for": "female",
        "img":"https://cdn.shopify.com/s/files/1/2617/9878/products/avenue-shopify-theme-womens-dresses-16_600x.jpg?v=1533820936"
    },
    {
        "id":"36",
        "title":"Basic Black Dress",
        "price": 24.99,
        "brand":"Keystone",
        "stock": 3,
        "rating":4.4,
        "details":"Feel your best with this simple, but stylish long sleeve T dress.  This basic dress is made from a soft Cotton and Polyester blend and is guaranteed not to shrink  or fade.",
        "category":"dress",
        "for": "female",
        "img":"https://cdn.shopify.com/s/files/1/2617/9878/products/avenue-shopify-theme-womens-dresses-17_600x.jpg?v=1533821085"
    },
    {
        "id":"37",
        "title":"Anchors Away Dress",
        "price": 29.99,
        "brand":"Keystone",
        "stock": 3,
        "rating":4.4,
        "details":"Feel your best with this simple, but stylish long sleeve T dress.  This basic dress is made from a soft Cotton and Polyester blend and is guaranteed not to shrink  or fade.",
        "category":"dress",
        "for": "female",
        "img":"https://cdn.shopify.com/s/files/1/2617/9878/products/avenue-shopify-theme-womens-dresses-15_600x.jpg?v=1533820805"
    },
    {
        "id":"71",
        "title":"Sweater Dress",
        "price": 19.99,
        "brand":"KD",
        "stock": 4,
        "rating":4.6,
        "details":"Feel your best with this simple, but stylish long sleeve T dress.  This basic dress is made from a soft Cotton and Polyester blend and is guaranteed not to shrink  or fade.",
        "category":"dress",
        "for": "female",
        "img":"https://cdn.shopify.com/s/files/1/2617/9878/products/avenue-shopify-theme-womens-dresses-7_600x.jpg?v=1533822547"
    },
    {
        "id":"38",
        "title":"Simple Dress",
        "price": 12.99,
        "brand":"Copper Thompson",
        "stock": 2,
        "rating":4.3,
        "details":"Feel your best with this simple, but stylish long sleeve T dress.  This basic dress is made from a soft Cotton and Polyester blend and is guaranteed not to shrink  or fade.",
        "category":"dress",
        "for": "female",
        "img":"https://cdn.shopify.com/s/files/1/2617/9878/products/avenue-shopify-theme-womens-dresses-10_600x.jpg?v=1533822003"
    },
    {
        "id":"39",
        "title":"Full Length Dress",
        "price": 19.99,
        "brand":"Keystone",
        "stock": 1,
        "rating":4.9,
        "details":"Your figure will look its best with this simple, but stylish full length dress.  This basic sleeveless dress is made from a soft Cotton and Polyester blend and is guaranteed not to shrink or fade.",
        "category":"dress",
        "for": "female",
        "img":"https://cdn.shopify.com/s/files/1/2617/9878/products/avenue-shopify-theme-womens-dresses-20_600x.jpg?v=1533821375"
    },
    {
        "id":"40",
        "title":"Retro Striped Dress",
        "price": 34.99,
        "brand":"Keystone",
        "stock": 5,
        "rating":4.2,
        "details":"Your figure will look its best with this simple, but stylish full length dress.  This basic sleeveless dress is made from a soft Cotton and Polyester blend and is guaranteed not to shrink or fade.",
        "category":"dress",
        "for": "female",
        "img":"https://cdn.shopify.com/s/files/1/2617/9878/products/avenue-shopify-theme-womens-dresses-4_600x.jpg?v=1533820763"
    },
    {
        "id":"41",
        "title":"Flowered Summer Dress",
        "price": 34.99,
        "brand":"Copper Thompson",
        "stock": 3,
        "rating":4.5,
        "details":"Your figure will look its best with this simple, but stylish full length dress.  This basic sleeveless dress is made from a soft Cotton and Polyester blend and is guaranteed not to shrink or fade.",
        "category":"dress",
        "for": "female",
        "img":"https://cdn.shopify.com/s/files/1/2617/9878/products/avenue-shopify-theme-womens-dresses-3_600x.jpg?v=1533820719"
    },
    {
        "id":"42",
        "title":"Lace Tank Top",
        "price": 18.75,
        "brand":"KD",
        "stock": 5,
        "rating":4.6,
        "details":"Your figure will look its best with this simple, but stylish full length dress.  This basic sleeveless dress is made from a soft Cotton and Polyester blend and is guaranteed not to shrink or fade.",
        "category":"tanks",
        "for": "female",
        "img":"https://cdn.shopify.com/s/files/1/2617/9878/products/avenue-shopify-theme-womens-tops-9_600x.jpg?v=1534170910"
    },
    {
        "id":"43",
        "title":"Ruffled Tank",
        "price": 19.99,
        "brand":"Keystone",
        "stock": 9,
        "rating":4.1,
        "details":"Your figure will look its best with this simple, but stylish full length dress.  This basic sleeveless dress is made from a soft Cotton and Polyester blend and is guaranteed not to shrink or fade.",
        "category":"tanks",
        "for": "female",
        "img":"https://cdn.shopify.com/s/files/1/2617/9878/products/avenue-shopify-theme-womens-tops-11_600x.jpg?v=1533824626"
    },
    {
        "id":"44",
        "title":"Floral Tank Top",
        "price": 18.45,
        "brand":"KD",
        "stock": 2,
        "rating":4.7,
        "details":"Your figure will look its best with this simple, but stylish full length dress.  This basic sleeveless dress is made from a soft Cotton and Polyester blend and is guaranteed not to shrink or fade.",
        "category":"tanks",
        "for": "female",
        "img":"https://cdn.shopify.com/s/files/1/2617/9878/products/avenue-shopify-theme-womens-tops-8_600x.jpg?v=1533824491"
    },
    {
        "id":"45",
        "title":"Basic Tank Top",
        "price": 9.95,
        "brand":"KD",
        "stock": 4,
        "rating":4.5,
        "details":"Look your best with this simple, but stylish tank.  This basic spaghetti strap tank is made from a soft Cotton and Polyester blend and is guaranteed not to shrink or fade.",
        "category":"tanks",
        "for": "female",
        "img":"https://cdn.shopify.com/s/files/1/2617/9878/products/avenue-shopify-theme-womens-tops-49_600x.jpg?v=1618260904"
    },
    {
        "id":"46",
        "title":"String Tank",
        "price": 16.99,
        "brand":"Copper Thompson",
        "stock": 3,
        "rating":4.3,
        "details":"Look your best with this simple, but stylish tank.  This basic spaghetti strap tank is made from a soft Cotton and Polyester blend and is guaranteed not to shrink or fade.",
        "category":"tanks",
        "for": "female",
        "img":"https://cdn.shopify.com/s/files/1/2617/9878/products/avenue-shopify-theme-womens-tops-30_600x.jpg?v=1533824717"
    },
    {
        "id":"47",
        "title":"Lacey Tank",
        "price": 12.95,
        "brand":"Copper Thompson",
        "stock": 5,
        "rating":4.7,
        "details":"Look your best with this simple, but stylish tank.  This basic spaghetti strap tank is made from a soft Cotton and Polyester blend and is guaranteed not to shrink or fade.",
        "category":"tanks",
        "for": "female",
        "img":"https://cdn.shopify.com/s/files/1/2617/9878/products/avenue-shopify-theme-womens-tops-23_600x.jpg?v=1533827595"
    },
    {
        "id":"48",
        "title":"Button Down Blouse",
        "price": 19.99,
        "brand":"Keystone",
        "stock": 3,
        "rating":4.5,
        "details":"Curl up with this simple, but stylish blouse.  This basic blouse is made from a soft Cotton and Polyester blend and is guaranteed not to shrink or fade.",
        "category":"blouse",
        "for": "female",
        "img":"https://cdn.shopify.com/s/files/1/2617/9878/products/avenue-shopify-theme-womens-tops-12_600x.jpg?v=1618925504"
    },
    {
        "id":"49",
        "title":"Lace Blouse",
        "price": 22.49,
        "brand":"KD",
        "stock": 5,
        "rating":4.0,
        "details":"Curl up with this simple, but stylish blouse.  This basic blouse is made from a soft Cotton and Polyester blend and is guaranteed not to shrink or fade.",
        "category":"blouse",
        "for": "female",
        "img":"https://cdn.shopify.com/s/files/1/2617/9878/products/avenue-shopify-theme-womens-tops-1_600x.jpg?v=1533823298"
    },
    {
        "id":"50",
        "title":"Comfy Cotton Blouse",
        "price": 19.49,
        "brand":"Copper Thompson",
        "stock": 2,
        "rating":4.5,
        "details":"Comfortable style in this simple, but stylish blouse.  This tie collar pullover is made from a soft Cotton and Polyester blend and is guaranteed not to shrink or fade.",
        "category":"blouse",
        "for": "female",
        "img":"https://cdn.shopify.com/s/files/1/2617/9878/products/avenue-shopify-theme-womens-tops-25_600x.jpg?v=1533824002"
    },
    {
        "id":"51",
        "title":"Polka Dot Blouse",
        "price": 22.99,
        "brand":"KD",
        "stock": 4,
        "rating":4.3,
        "details":"Comfortable style in this simple, but stylish blouse.  This tie collar pullover is made from a soft Cotton and Polyester blend and is guaranteed not to shrink or fade.",
        "category":"blouse",
        "for": "female",
        "img":"https://cdn.shopify.com/s/files/1/2617/9878/products/avenue-shopify-theme-womens-tops-29_600x.jpg?v=1533823418"
    },
    {
        "id":"52",
        "title":"Plaid Skirt",
        "price": 17.99,
        "brand":"KD",
        "stock": 4,
        "rating":4.5,
        "details":"Comfortable style in this simple, but stylish blouse.  This tie collar pullover is made from a soft Cotton and Polyester blend and is guaranteed not to shrink or fade.",
        "category":"skirt",
        "for": "female",
        "img":"https://cdn.shopify.com/s/files/1/2617/9878/products/avenue-shopify-theme-womens-bottoms-35_600x.jpg?v=1533917734"
    },
    {
        "id":"53",
        "title":"Shimmery Skirt",
        "price": 15.99,
        "brand":"Keystone",
        "stock": 5,
        "rating":4.1,
        "details":"Comfortable style in this simple, but stylish blouse.  This tie collar pullover is made from a soft Cotton and Polyester blend and is guaranteed not to shrink or fade.",
        "category":"skirt",
        "for": "female",
        "img":"https://cdn.shopify.com/s/files/1/2617/9878/products/avenue-shopify-theme-womens-bottoms-24_600x.jpg?v=1533818046"
    },
    {
        "id":"54",
        "title":"Casual Tie Skirt",
        "price": 17.95,
        "brand":"Copper Thompson",
        "stock": 9,
        "rating":4.0,
        "details":"Your legs will look their best with this stylish skirt  This above the knee skirt is made from a soft Cotton and Polyester blend and is guaranteed not to shrink or fade.",
        "category":"skirt",
        "for": "female",
        "img":"https://cdn.shopify.com/s/files/1/2617/9878/products/avenue-shopify-theme-womens-bottoms-15_600x.jpg?v=1533819372"
    },
    {
        "id":"55",
        "title":"Plain Front Skirt",
        "price": 14.95,
        "brand":"Copper Thompson",
        "stock": 3,
        "rating":4.5,
        "details":"Look your best with this simple, but stylish skirt.  This plain front option is made from a soft Cotton and Polyester blend and is guaranteed not to shrink or fade.",
        "category":"skirt",
        "for": "female",
        "img":"https://cdn.shopify.com/s/files/1/2617/9878/products/avenue-shopify-theme-womens-bottoms-1_600x.jpg?v=1533819182"
    },
    {
        "id":"56",
        "title":"Ruffled Skirt",
        "price": 24.95,
        "brand":"Keystone",
        "stock": 5,
        "rating":4.3,
        "details":"Look your best with this simple, but stylish skirt.  This plain front option is made from a soft Cotton and Polyester blend and is guaranteed not to shrink or fade.",
        "category":"skirt",
        "for": "female",
        "img":"https://cdn.shopify.com/s/files/1/2617/9878/products/avenue-shopify-theme-womens-bottoms-29_600x.jpg?v=1533818166"
    },
    {
        "id":"57",
        "title":"Printed Skirt",
        "price": 20.99,
        "brand":"KD",
        "stock": 7,
        "rating":4.9,
        "details":"Look your best with this simple, but stylish skirt.  This plain front option is made from a soft Cotton and Polyester blend and is guaranteed not to shrink or fade.",
        "category":"skirt",
        "for": "female",
        "img":"https://cdn.shopify.com/s/files/1/2617/9878/products/avenue-shopify-theme-womens-bottoms-23_600x.jpg?v=1533818003"
    },
    {
        "id":"58",
        "title":"Full Length Skirt",
        "price": 12.99,
        "brand":"KD",
        "stock": 2,
        "rating":4.3,
        "details":"Look your best with this simple, but stylish skirt.  This plain front option is made from a soft Cotton and Polyester blend and is guaranteed not to shrink or fade.",
        "category":"skirt",
        "for": "female",
        "img":"https://cdn.shopify.com/s/files/1/2617/9878/products/avenue-shopify-theme-womens-bottoms-14_600x.jpg?v=1533818660"
    },
    {
        "id":"59",
        "title":"Distressed Jeans",
        "price": 14.99,
        "brand":"KD",
        "stock": 5,
        "rating":4.5,
        "details":"Look your best with this simple, but stylish skirt.  This plain front option is made from a soft Cotton and Polyester blend and is guaranteed not to shrink or fade.",
        "category":"pants",
        "for": "kids",
        "img":"https://cdn.shopify.com/s/files/1/2617/9878/products/avenue-shopify-theme-boys-clothing-4_600x.jpg?v=1533681837"
    },
    {
        "id":"60",
        "title":"Dark Jeans",
        "price": 11.95,
        "brand":"Keystone",
        "stock": 3,
        "rating":4.9,
        "details":"Look your best with this simple, but stylish skirt.  This plain front option is made from a soft Cotton and Polyester blend and is guaranteed not to shrink or fade.",
        "category":"pants",
        "for": "kids",
        "img":"https://cdn.shopify.com/s/files/1/2617/9878/products/avenue-shopify-theme-boys-clothing-19_600x.jpg?v=1533737962"
    },
    {
        "id":"61",
        "title":"Pink Scarf Jeans",
        "price": 9.95,
        "brand":"Copper Thompson",
        "stock": 2,
        "rating":4.0,
        "details":"Look your best with this simple, but stylish skirt.  This plain front option is made from a soft Cotton and Polyester blend and is guaranteed not to shrink or fade.",
        "category":"pants",
        "for": "kids",
        "img":"https://cdn.shopify.com/s/files/1/2617/9878/products/avenue-shopify-theme-girls-clothing-16_600x.jpg?v=1533744627"
    },
    {
        "id":"62",
        "title":"Drawstring Sweatpants",
        "price": 8.95,
        "brand":"KD",
        "stock": 9,
        "rating":4.2,
        "details":"Look your best with this simple, but stylish skirt.  This plain front option is made from a soft Cotton and Polyester blend and is guaranteed not to shrink or fade.",
        "category":"pants",
        "for": "kids",
        "img":"https://cdn.shopify.com/s/files/1/2617/9878/products/avenue-shopify-theme-boys-clothing-27_600x.jpg?v=1533737688"
    },
    {
        "id":"63",
        "title":"Multi Pocket Jeans",
        "price": 13.99,
        "brand":"Copper Thompson",
        "stock": 4,
        "rating":4.5,
        "details":"Look your best with this simple, but stylish skirt.  This plain front option is made from a soft Cotton and Polyester blend and is guaranteed not to shrink or fade.",
        "category":"pants",
        "for": "kids",
        "img":"https://cdn.shopify.com/s/files/1/2617/9878/products/avenue-shopify-theme-girls-clothing-14_600x.jpg?v=1533744562"
    },
    {
        "id":"64",
        "title":"White Jeans",
        "price": 8.45,
        "brand":"Keystone",
        "stock": 5,
        "rating":4.9,
        "details":"Look your best with this simple, but stylish skirt.  This plain front option is made from a soft Cotton and Polyester blend and is guaranteed not to shrink or fade.",
        "category":"pants",
        "for": "kids",
        "img":"https://cdn.shopify.com/s/files/1/2617/9878/products/avenue-shopify-theme-girls-clothing-15_600x.jpg?v=1533744666"
    },
    {
        "id":"65",
        "title":"Basic Girls T",
        "price": 7.45,
        "brand":"Keystone",
        "stock": 6,
        "rating":4.0,
        "details":"Help her look her best with this simple, but stylish t-shirt.  This basic short-sleeve tee is made from a soft Cotton and Polyester blend and is guaranteed not to shrink or fade.",
        "category":"shirts",
        "for": "kids",
        "img":"https://cdn.shopify.com/s/files/1/2617/9878/products/avenue-shopify-theme-girls-clothing-24_600x.jpg?v=1533743623"
    },
    {
        "id":"66",
        "title":"Basic Short Sleeve",
        "price": 6.45,
        "brand":"KD",
        "stock": 3,
        "rating":4.4,
        "details":"Help her look her best with this simple, but stylish t-shirt.  This basic short-sleeve tee is made from a soft Cotton and Polyester blend and is guaranteed not to shrink or fade.",
        "category":"shirts",
        "for": "kids",
        "img":"https://cdn.shopify.com/s/files/1/2617/9878/products/avenue-shopify-theme-girls-clothing-23_600x.jpg?v=1533743234"
    },
    {
        "id":"67",
        "title":"Short Sleeve Button Down",
        "price": 9.95,
        "brand":"KD",
        "stock": 5,
        "rating":4.6,
        "details":"Help him look his best with this simple, but stylish t-shirt.  This basic short-sleeve tee is made from a soft Cotton and Polyester blend and is guaranteed not to shrink  or fade.",
        "category":"shirts",
        "for": "kids",
        "img":"https://cdn.shopify.com/s/files/1/2617/9878/products/avenue-shopify-theme-boys-clothing-8_600x.jpg?v=1533680807"
    },
    {
        "id":"68",
        "title":"Short Sleeve Striped V-Neck",
        "price": 7.95,
        "brand":"Copper Thompson",
        "stock": 8,
        "rating":4.3,
        "details":"Help him look his best with this simple, but stylish t-shirt.  This basic short-sleeve tee is made from a soft Cotton and Polyester blend and is guaranteed not to shrink  or fade.",
        "category":"shirts",
        "for": "kids",
        "img":"https://cdn.shopify.com/s/files/1/2617/9878/products/avenue-shopify-theme-boys-clothing-25_600x.jpg?v=1533680665"
    },
    {
        "id":"69",
        "title":"Boys Basic T",
        "price": 6.95,
        "brand":"Copper Thompson",
        "stock": 6,
        "rating":4.5,
        "details":"Help him look his best with this simple, but stylish t-shirt.  This basic short-sleeve tee is made from a soft Cotton and Polyester blend and is guaranteed not to shrink  or fade.",
        "category":"shirts",
        "for": "kids",
        "img":"https://cdn.shopify.com/s/files/1/2617/9878/products/avenue-shopify-theme-boys-clothing-17_600x.jpg?v=1551728861"
    },
    {
        "id":"70",
        "title":"Aqua Tank",
        "price": 11.95,
        "brand":"Copper Thompson",
        "stock": 5,
        "rating":4.7,
        "details":"Help her look his best with this simple, but stylish t-shirt.  This basic short-sleeve tee is made from a soft Cotton and Polyester blend and is guaranteed not to shrink  or fade.",
        "category":"shirts",
        "for": "kids",
        "img":"https://cdn.shopify.com/s/files/1/2617/9878/products/avenue-shopify-theme-girls-clothing-9_600x.jpg?v=1533743183"
    }
]